scrinet/__init__.py
scrinet/logger.py
scrinet/utils.py
scrinet/analysis/__init__.py
scrinet/analysis/frequencyseries.py
scrinet/analysis/frequencyseries_batch.py
scrinet/analysis/matchedfilter.py
scrinet/analysis/matchedfilter_batch.py
scrinet/analysis/tf_fft.py
scrinet/analysis/tf_fft_batch.py
scrinet/analysis/timeseries.py
scrinet/analysis/timeseries_batch.py
scrinet/analysis/utils.py
scrinet/fits/__init__.py
scrinet/fits/gprfit.py
scrinet/fits/nn.py
scrinet/fits/poly.py
scrinet/fits/scale.py
scrinet/greedy/__init__.py
scrinet/greedy/greedyrb.py
scrinet/interfaces/__init__.py
scrinet/interfaces/lalutils.py
scrinet/interfaces/rotations.py
scrinet/pn/__init__.py
scrinet/pn/pn.py
scrinet/results/__init__.py
scrinet/results/results.py
scrinet/sample/__init__.py
scrinet/sample/kernels.py
scrinet/sample/likelihood.py
scrinet/sample/priors.py
scrinet/sample/sample_helpers.py
scrinet/sample/tmp_SoftClip.py
scrinet/surrogate/__init__.py
scrinet/surrogate/surrogate.py
scrinet/workflow/__init__.py
scrinet/workflow/condor.py
scrinet/workflow/generators.py
scrinet/workflow/pipe_utils.py
scrinet-0.1.4.data/scripts/scrinet_build_rb
scrinet-0.1.4.data/scripts/scrinet_combine_wf_data
scrinet-0.1.4.data/scripts/scrinet_evaluate_7d_coprec_model
scrinet-0.1.4.data/scripts/scrinet_evaluate_coprec_model
scrinet-0.1.4.data/scripts/scrinet_evaluate_model
scrinet-0.1.4.data/scripts/scrinet_fit
scrinet-0.1.4.data/scripts/scrinet_gen_ts_data
scrinet-0.1.4.data/scripts/scrinet_gen_wf_data_2d_non_prec
scrinet-0.1.4.data/scripts/scrinet_gen_wf_data_3d_non_prec
scrinet-0.1.4.data/scripts/scrinet_gen_wf_data_3d_prec_single_spin
scrinet-0.1.4.data/scripts/scrinet_gen_wf_data_3d_prec_single_spin_coprec
scrinet-0.1.4.data/scripts/scrinet_gen_wf_data_7d_prec_single_spin_coprec
scrinet-0.1.4.data/scripts/scrinet_gen_wf_data_non_spinning
scrinet-0.1.4.data/scripts/scrinet_make_webpage
scrinet-0.1.4.data/scripts/scrinet_make_workflow
scrinet-0.1.4.data/scripts/scrinet_representation_error
scrinet-0.1.4.dist-info/LICENSE
scrinet-0.1.4.dist-info/METADATA
scrinet-0.1.4.dist-info/WHEEL
scrinet-0.1.4.dist-info/top_level.txt
scrinet-0.1.4.dist-info/RECORD
