Metadata-Version: 2.1
Name: scrinet
Version: 0.1.4
Summary: Modelling
Home-page: https://gitlab.com/SpaceTimeKhantinuum/scrinet
Author: Sebastian Khan, Rhys Green
Author-email: khans22@cardiff.ac.uk, greenr10@cardiff.ac.uk
License: UNKNOWN
Platform: UNKNOWN
